rag_toolkit/__init__.py
rag_toolkit/client.py
rag_toolkit/config.py
rag_toolkit/data_loader.py
rag_toolkit/embedding.py
rag_toolkit/generator.py
rag_toolkit/google_models.py
rag_toolkit/initialize_llm.py
rag_toolkit/logging.py
rag_toolkit/pipeline.py
rag_toolkit/retriever.py
rag_toolkit/routing.py
rag_toolkit/utils.py
rag_toolkit/vector_store.py
rag_toolkit-0.1.1.dist-info/LICENSE
rag_toolkit-0.1.1.dist-info/METADATA
rag_toolkit-0.1.1.dist-info/WHEEL
rag_toolkit-0.1.1.dist-info/top_level.txt
rag_toolkit-0.1.1.dist-info/RECORD
