Metadata-Version: 2.1
Name: rag-toolkit
Version: 0.1.1
Summary: A library for building Retrieval-Augmented Generation pipelines.
Home-page: https://github.com/youssef-yasser-ali/rag-toolkit
Author: Your Name
Author-email: yyasser849@gmail.com
Classifier: Programming Language :: Python :: 3
Classifier: License :: OSI Approved :: Apache Software License
Classifier: Operating System :: OS Independent
Requires-Python: >=3.7
License-File: LICENSE
Requires-Dist: langchain (==0.3.12)
Requires-Dist: langchain-community (==0.3.12)
Requires-Dist: langsmith (==0.1.140)
Requires-Dist: chromadb (==0.5.20)
Requires-Dist: langchain-google-genai (==2.0.4)
Requires-Dist: pydantic (==2.9.2)
Requires-Dist: pypdf (==5.1.0)
